nupass/__init__.py
nupass/nupass.py
nupass/script.py
nupass/wordlist.txt
nupass-1.0.0.dist-info/LICENSE
nupass-1.0.0.dist-info/METADATA
nupass-1.0.0.dist-info/WHEEL
nupass-1.0.0.dist-info/entry_points.txt
nupass-1.0.0.dist-info/top_level.txt
nupass-1.0.0.dist-info/RECORD
